llm_plugin_pdf.py
llm_plugin_pdf-0.1.dist-info/licenses/LICENSE
llm_plugin_pdf-0.1.dist-info/METADATA
llm_plugin_pdf-0.1.dist-info/WHEEL
llm_plugin_pdf-0.1.dist-info/entry_points.txt
llm_plugin_pdf-0.1.dist-info/top_level.txt
llm_plugin_pdf-0.1.dist-info/RECORD
