Metadata-Version: 2.4
Name: llm-plugin-pdf
Version: 0.1
Summary: LLM plugin for loading text from PDF files (local or URL)
Author: Agusti F.
License-Expression: Apache-2.0
Project-URL: Homepage, https://github.com/agustif/llm-pdf-plugin
Project-URL: Changelog, https://github.com/agustif/llm-pdf-plugin/releases
Project-URL: Issues, https://github.com/agustif/llm-pdf-plugin/issues
Project-URL: CI, https://github.com/agustif/llm-pdf-plugin/actions
Requires-Python: >=3.9
License-File: LICENSE
Requires-Dist: llm
Requires-Dist: PyMuPDF
Requires-Dist: requests
Provides-Extra: test
Requires-Dist: pytest; extra == "test"
Dynamic: license-file
